temfield/EUT.py
temfield/TEMField.py
temfield/TestSusceptibility.py
temfield/__init__.py
temfield/mainwindow.py
temfield/mainwindow.ui
temfield-0.2.1.dist-info/licenses/LICENSE
temfield-0.2.1.dist-info/WHEEL
temfield-0.2.1.dist-info/entry_points.txt
temfield-0.2.1.dist-info/METADATA
temfield-0.2.1.dist-info/RECORD
