Metadata-Version: 2.4
Name: temfield
Version: 0.2.1
Summary: Radiated EMC susceptibility measurements in (G)TEM wavegides using mpylab
Keywords: EMC,measurements,laboratory
Author: Hans Georg Krauthäuser
Author-email: Hans Georg Krauthäuser <hgk@ieee.org>
License-Expression: GPL-3.0-or-later
License-File: LICENSE
Classifier: Development Status :: 4 - Beta
Classifier: Intended Audience :: Developers
Classifier: Intended Audience :: Education
Classifier: Intended Audience :: Science/Research
Classifier: License :: OSI Approved :: GNU General Public License v3 or later (GPLv3+)
Classifier: Topic :: Scientific/Engineering
Classifier: Programming Language :: Python :: 3
Classifier: Programming Language :: Python :: 3.8
Classifier: Programming Language :: Python :: 3.9
Classifier: Programming Language :: Python :: 3.10
Classifier: Programming Language :: Python :: 3.11
Classifier: Programming Language :: Python :: 3.12
Classifier: Programming Language :: Python :: 3.13
Requires-Dist: matplotlib>=3.7.5
Requires-Dist: mpylab>=0.9.1
Requires-Dist: numpy>=1.24.4
Requires-Dist: pyside6>=6.6.3.1
Maintainer: Hans Georg Krauthäuser
Maintainer-email: Hans Georg Krauthäuser <hgk@ieee.org>
Requires-Python: >=3.8
Project-URL: Repository, https://github.com/hgkdd/TEMField
